Workbook

Sheet Resumen
A1: Business Case — ROI / Payback (ACQC Repsol Puertollano)
A2: Modelo de ROI basado en supuestos explícitos y resultados esperados (no medidos). Ajustar con datos de historian/LIMS, QA y cotizaciones.
A4: Escenario para vista rápida | B4: Base | C4: Nota: la tabla inferior calcula los 3 escenarios.
A6: Vista rápida (escenario seleccionado)
A7: Métrica | B7: Valor
A8: Beneficios anuales (total) | B8: =INDEX($B$22:$D$22,1, MATCH($B$4, $B$18:$D$18, 0))
A9: OPEX anual | B9: =INDEX($B$23:$D$23,1, MATCH($B$4, $B$18:$D$18, 0))
A10: Beneficio neto anual (beneficios - OPEX) | B10: =INDEX($B$24:$D$24,1, MATCH($B$4, $B$18:$D$18, 0))
A11: CAPEX total | B11: =INDEX($B$25:$D$25,1, MATCH($B$4, $B$18:$D$18, 0))
A12: Payback simple | B12: =INDEX($B$26:$D$26,1, MATCH($B$4, $B$18:$D$18, 0))
A13: ROI anual simple | B13: =INDEX($B$27:$D$27,1, MATCH($B$4, $B$18:$D$18, 0))
A14: NPV (vida, descuento) | B14: =INDEX($B$30:$D$30,1, MATCH($B$4, $B$18:$D$18, 0))
A17: Comparativa por escenario
A18: Métrica | B18: Conservador | C18: Base | D18: Ambicioso | E18: Notas
A19: Beneficios energía | B19: =Beneficios_Energia!B13 | C19: =Beneficios_Energia!C13 | D19: =Beneficios_Energia!D13 | E19: Optimización segura: ahorro energético esperado (aplica adopción).
A20: Beneficios calidad | B20: =Beneficios_Calidad!B12 | C20: =Beneficios_Calidad!C12 | D20: =Beneficios_Calidad!D12 | E20: Estimación por reducción de scrap/rework (validar con QA).
A21: Beneficios disponibilidad+rto | B21: =Beneficios_Disponibilidad!B16 | C21: =Beneficios_Disponibilidad!C16 | D21: =Beneficios_Disponibilidad!D16 | E21: Incluye reducción de downtime + mejora throughput (aplica adopción).
A22: Beneficios anuales (total) | B22: =B19+B20+B21 | C22: =C19+C20+C21 | D22: =D19+D20+D21
A23: OPEX anual | B23: =Costes!B21 | C23: =Costes!C21 | D23: =Costes!D21
A24: Beneficio neto anual | B24: =B22-B23 | C24: =C22-C23 | D24: =D22-D23
A25: CAPEX total | B25: =Costes!B13 | C25: =Costes!C13 | D25: =Costes!D13
A26: Payback simple | B26: =IF(B24<=0,"—",B25/B24) | C26: =IF(C24<=0,"—",C25/C24) | D26: =IF(D24<=0,"—",D25/D24)
A27: ROI anual simple | B27: =IF(B25=0,"—",B24/B25*100) | C27: =IF(C25=0,"—",C24/C25*100) | D27: =IF(D25=0,"—",D24/D25*100)
A28: Vida económica (años) | B28: =INDEX(Supuestos!$E$4:$G$31, MATCH("K03", Supuestos!$A$4:$A$31, 0), MATCH(B$18, Supuestos!$E$3:$G$3, 0)) | C28: =INDEX(Supuestos!$E$4:$G$31, MATCH("K03", Supuestos!$A$4:$A$31, 0), MATCH(C$18, Supuestos!$E$3:$G$3, 0)) | D28: =INDEX(Supuestos!$E$4:$G$31, MATCH("K03", Supuestos!$A$4:$A$31, 0), MATCH(D$18, Supuestos!$E$3:$G$3, 0))
A29: Tasa de descuento | B29: =INDEX(Supuestos!$E$4:$G$31, MATCH("K04", Supuestos!$A$4:$A$31, 0), MATCH(B$18, Supuestos!$E$3:$G$3, 0)) | C29: =INDEX(Supuestos!$E$4:$G$31, MATCH("K04", Supuestos!$A$4:$A$31, 0), MATCH(C$18, Supuestos!$E$3:$G$3, 0)) | D29: =INDEX(Supuestos!$E$4:$G$31, MATCH("K04", Supuestos!$A$4:$A$31, 0), MATCH(D$18, Supuestos!$E$3:$G$3, 0))
A30: NPV | B30: =IF(B24<=0,"—",-(B25)+IF(B29=0,B24*B28,B24*(1-(1+B29/100)^(-B28))/(B29/100))) | C30: =IF(C24<=0,"—",-(C25)+IF(C29=0,C24*C28,C24*(1-(1+C29/100)^(-C28))/(C29/100))) | D30: =IF(D24<=0,"—",-(D25)+IF(D29=0,D24*D28,D24*(1-(1+D29/100)^(-D28))/(D29/100))) | E30: NPV con beneficio neto anual constante (simplificación).

Sheet Supuestos
A1: Supuestos (Single Source of Truth) — ACQC Business Case
A2: Regla: todo número usado en el modelo debe derivarse de esta hoja y tener fuente o supuesto explicitado.
A3: ID | B3: Categoría | C3: Parámetro | D3: Unidad | E3: Conservador | F3: Base | G3: Ambicioso | H3: Tipo | I3: Fuente/Justificación | J3: Responsable | K3: URL/Referencia
A4: K00 | B4: Constantes | C4: Horas por año | D4: h/año | E4: 8760 | F4: 8760 | G4: 8760 | H4: SUPUESTO | I4: Constante de calendario (sin año específico). | J4: TFM | K4: https://github.com/tangodelta217/ACQC
A5: K01 | B5: Constantes | C5: Factor sensibilidad (bajo) | D5: x | E5: 0.8 | F5: 0.8 | G5: 0.8 | H5: SUPUESTO | I5: Definición interna: ±20% (bajo). | J5: TFM | K5: https://github.com/tangodelta217/ACQC
A6: K02 | B6: Constantes | C6: Factor sensibilidad (alto) | D6: x | E6: 1.2 | F6: 1.2 | G6: 1.2 | H6: SUPUESTO | I6: Definición interna: ±20% (alto). | J6: TFM | K6: https://github.com/tangodelta217/ACQC
A7: K03 | B7: Finanzas | C7: Vida económica del caso | D7: años | E7: 3 | F7: 5 | G7: 7 | H7: SUPUESTO | I7: Supuesto estándar para pilotos industriales; ajustar a política financiera. | J7: Finanzas | K7: https://github.com/tangodelta217/ACQC
A8: K04 | B8: Finanzas | C8: Tasa de descuento (WACC/CoC) | D8: % | E8: 10 | F8: 8 | G8: 6 | H8: SUPUESTO | I8: Supuesto inicial; reemplazar por tasa corporativa. | J8: Finanzas | K8: https://github.com/tangodelta217/ACQC
A9: A01 | B9: Operación | C9: Adopción efectiva de recomendaciones (human-in-the-loop) | D9: % | E9: 40 | F9: 60 | G9: 80 | H9: SUPUESTO | I9: Modo asesor con operador en el bucle; adopción parcial es realista. | J9: Operación | K9: https://github.com/tangodelta217/ACQC
A10: A02 | B10: Operación | C10: Horas de downtime anual atribuible a incidencias de medición/calidad | D10: h/año | E10: 60 | F10: 40 | G10: 20 | H10: SUPUESTO | I10: Depende de histórico local; establecer con OT/Operación. | J10: OT/Operación | K10: https://github.com/tangodelta217/ACQC
A11: A03 | B11: Operación | C11: Reducción de downtime por fallback + detección (ACQC) | D11: % | E11: 10 | F11: 25 | G11: 40 | H11: SUPUESTO | I11: Se incluyen flujos degradados (fallback) y observabilidad; cuantificar con incidentes reales. | J11: OT/Operación | K11: https://github.com/tangodelta217/ACQC
A12: P01 | B12: Producción | C12: Producción anual impactada (corriente/unidad objetivo) | D12: t/año | E12: 80000 | F12: 150000 | G12: 250000 | H12: SUPUESTO | I12: Requiere definir unidad y corriente en Puertollano; placeholder editable. | J12: Producción | K12: https://github.com/tangodelta217/ACQC
A13: P02 | B13: Producción | C13: Margen de contribución por tonelada (producto afectado) | D13: €/t | E13: 30 | F13: 50 | G13: 80 | H13: SUPUESTO | I13: Depende de slate y mercado; usar contabilidad de gestión. | J13: Finanzas | K13: https://github.com/tangodelta217/ACQC
A14: P03 | B14: Producción | C14: Mejora de throughput/rendimiento por optimización (esperada) | D14: % | E14: 1 | F14: 3 | G14: 5 | H14: FUENTE | I14: Doc ACQC_Optimizacion.pdf (2026): mejora esperada de throughput/rendimiento ~3% (resultados esperados; validar). | J14: Proceso | K14: https://github.com/tangodelta217/ACQC
A15: E01 | B15: Energía | C15: Consumo energético específico base | D15: GJ/t | E15: 1.5 | F15: 2 | G15: 2.5 | H15: SUPUESTO | I15: Depende de la unidad (hidrotratamiento/blending/etc.); estimación inicial editable. | J15: Energía/Proceso | K15: https://github.com/tangodelta217/ACQC
... A31: O04 | B31: Costes (OPEX) | C31: Infraestructura IT (almacenamiento, backups, licencias) | D31: €/año | E31: 3000 | F31: 8000 | G31: 15000 | H31: SUPUESTO | I31: Puede ser 0 si se usa infraestructura existente; confirmar. | J31: IT | K31: https://github.com/tangodelta217/ACQC

Sheet Beneficios_Energia
A1: Beneficios — Energía (optimización segura en modo asesor)
A2: Beneficios calculados como resultados esperados (no medidos). Se aplican con factor de adopción del modo asesor.
A4: Concepto | B4: Conservador | C4: Base | D4: Ambicioso | E4: Unidad | F4: ID supuesto | G4: Fuente | H4: Notas
A5: Producción anual impactada | B5: =INDEX(Supuestos!$E$4:$G$31, MATCH($F5, Supuestos!$A$4:$A$31, 0), MATCH(B$4, Supuestos!$E$3:$G$3, 0)) | C5: =INDEX(Supuestos!$E$4:$G$31, MATCH($F5, Supuestos!$A$4:$A$31, 0), MATCH(C$4, Supuestos!$E$3:$G$3, 0)) | D5: =INDEX(Supuestos!$E$4:$G$31, MATCH($F5, Supuestos!$A$4:$A$31, 0), MATCH(D$4, Supuestos!$E$3:$G$3, 0)) | E5: t/año | F5: P01 | G5: =IF($F5="","Derivado (fórmula)","Ver Supuestos (ID "&$F5&")")
A6: Consumo específico base | B6: =INDEX(Supuestos!$E$4:$G$31, MATCH($F6, Supuestos!$A$4:$A$31, 0), MATCH(B$4, Supuestos!$E$3:$G$3, 0)) | C6: =INDEX(Supuestos!$E$4:$G$31, MATCH($F6, Supuestos!$A$4:$A$31, 0), MATCH(C$4, Supuestos!$E$3:$G$3, 0)) | D6: =INDEX(Supuestos!$E$4:$G$31, MATCH($F6, Supuestos!$A$4:$A$31, 0), MATCH(D$4, Supuestos!$E$3:$G$3, 0)) | E6: GJ/t | F6: E01 | G6: =IF($F6="","Derivado (fórmula)","Ver Supuestos (ID "&$F6&")")
A7: Precio energía promedio | B7: =INDEX(Supuestos!$E$4:$G$31, MATCH($F7, Supuestos!$A$4:$A$31, 0), MATCH(B$4, Supuestos!$E$3:$G$3, 0)) | C7: =INDEX(Supuestos!$E$4:$G$31, MATCH($F7, Supuestos!$A$4:$A$31, 0), MATCH(C$4, Supuestos!$E$3:$G$3, 0)) | D7: =INDEX(Supuestos!$E$4:$G$31, MATCH($F7, Supuestos!$A$4:$A$31, 0), MATCH(D$4, Supuestos!$E$3:$G$3, 0)) | E7: €/GJ | F7: E02 | G7: =IF($F7="","Derivado (fórmula)","Ver Supuestos (ID "&$F7&")")
A8: Coste energía anual base | B8: =B5*B6*B7 | C8: =C5*C6*C7 | D8: =D5*D6*D7 | E8: € | G8: =IF($F8="","Derivado (fórmula)","Ver Supuestos (ID "&$F8&")") | H8: P01*E01*E02
A9: % ahorro energía por optimización | B9: =INDEX(Supuestos!$E$4:$G$31, MATCH($F9, Supuestos!$A$4:$A$31, 0), MATCH(B$4, Supuestos!$E$3:$G$3, 0)) | C9: =INDEX(Supuestos!$E$4:$G$31, MATCH($F9, Supuestos!$A$4:$A$31, 0), MATCH(C$4, Supuestos!$E$3:$G$3, 0)) | D9: =INDEX(Supuestos!$E$4:$G$31, MATCH($F9, Supuestos!$A$4:$A$31, 0), MATCH(D$4, Supuestos!$E$3:$G$3, 0)) | E9: % | F9: E03 | G9: =IF($F9="","Derivado (fórmula)","Ver Supuestos (ID "&$F9&")")
A10: Adopción efectiva (human-in-the-loop) | B10: =INDEX(Supuestos!$E$4:$G$31, MATCH($F10, Supuestos!$A$4:$A$31, 0), MATCH(B$4, Supuestos!$E$3:$G$3, 0)) | C10: =INDEX(Supuestos!$E$4:$G$31, MATCH($F10, Supuestos!$A$4:$A$31, 0), MATCH(C$4, Supuestos!$E$3:$G$3, 0)) | D10: =INDEX(Supuestos!$E$4:$G$31, MATCH($F10, Supuestos!$A$4:$A$31, 0), MATCH(D$4, Supuestos!$E$3:$G$3, 0)) | E10: % | F10: A01 | G10: =IF($F10="","Derivado (fórmula)","Ver Supuestos (ID "&$F10&")")
A11: Ahorro anual energía (realizado) | B11: =B8*B9/100*B10/100 | C11: =C8*C9/100*C10/100 | D11: =D8*D9/100*D10/100 | E11: € | G11: =IF($F11="","Derivado (fórmula)","Ver Supuestos (ID "&$F11&")") | H11: Coste_base*%ahorro*adopción
A13: Ahorro anual total (energía) | B13: =B11 | C13: =C11 | D13: =D11 | E13: €

Sheet Beneficios_Calidad
A1: Beneficios — Calidad (scrap/rework/lotes)
A2: Beneficios estimados por reducción de scrap/rework y menor probabilidad de lotes fuera de especificación (resultados esperados).
A4: Concepto | B4: Conservador | C4: Base | D4: Ambicioso | E4: Unidad | F4: ID supuesto | G4: Fuente | H4: Notas
A5: Producción anual impactada | B5: =INDEX(Supuestos!$E$4:$G$31, MATCH($F5, Supuestos!$A$4:$A$31, 0), MATCH(B$4, Supuestos!$E$3:$G$3, 0)) | C5: =INDEX(Supuestos!$E$4:$G$31, MATCH($F5, Supuestos!$A$4:$A$31, 0), MATCH(C$4, Supuestos!$E$3:$G$3, 0)) | D5: =INDEX(Supuestos!$E$4:$G$31, MATCH($F5, Supuestos!$A$4:$A$31, 0), MATCH(D$4, Supuestos!$E$3:$G$3, 0)) | E5: t/año | F5: P01 | G5: =IF($F5="","Derivado (fórmula)","Ver Supuestos (ID "&$F5&")")
A6: Tasa scrap/rework base | B6: =INDEX(Supuestos!$E$4:$G$31, MATCH($F6, Supuestos!$A$4:$A$31, 0), MATCH(B$4, Supuestos!$E$3:$G$3, 0)) | C6: =INDEX(Supuestos!$E$4:$G$31, MATCH($F6, Supuestos!$A$4:$A$31, 0), MATCH(C$4, Supuestos!$E$3:$G$3, 0)) | D6: =INDEX(Supuestos!$E$4:$G$31, MATCH($F6, Supuestos!$A$4:$A$31, 0), MATCH(D$4, Supuestos!$E$3:$G$3, 0)) | E6: % | F6: Q01 | G6: =IF($F6="","Derivado (fórmula)","Ver Supuestos (ID "&$F6&")")
A7: Coste incremental scrap/rework | B7: =INDEX(Supuestos!$E$4:$G$31, MATCH($F7, Supuestos!$A$4:$A$31, 0), MATCH(B$4, Supuestos!$E$3:$G$3, 0)) | C7: =INDEX(Supuestos!$E$4:$G$31, MATCH($F7, Supuestos!$A$4:$A$31, 0), MATCH(C$4, Supuestos!$E$3:$G$3, 0)) | D7: =INDEX(Supuestos!$E$4:$G$31, MATCH($F7, Supuestos!$A$4:$A$31, 0), MATCH(D$4, Supuestos!$E$3:$G$3, 0)) | E7: €/t | F7: Q02 | G7: =IF($F7="","Derivado (fórmula)","Ver Supuestos (ID "&$F7&")")
A8: Coste anual scrap/rework (base) | B8: =B5*B6/100*B7 | C8: =C5*C6/100*C7 | D8: =D5*D6/100*D7 | E8: € | G8: =IF($F8="","Derivado (fórmula)","Ver Supuestos (ID "&$F8&")") | H8: P01*Q01*Q02
A9: Reducción scrap/rework por ACQC | B9: =INDEX(Supuestos!$E$4:$G$31, MATCH($F9, Supuestos!$A$4:$A$31, 0), MATCH(B$4, Supuestos!$E$3:$G$3, 0)) | C9: =INDEX(Supuestos!$E$4:$G$31, MATCH($F9, Supuestos!$A$4:$A$31, 0), MATCH(C$4, Supuestos!$E$3:$G$3, 0)) | D9: =INDEX(Supuestos!$E$4:$G$31, MATCH($F9, Supuestos!$A$4:$A$31, 0), MATCH(D$4, Supuestos!$E$3:$G$3, 0)) | E9: % | F9: Q03 | G9: =IF($F9="","Derivado (fórmula)","Ver Supuestos (ID "&$F9&")")
A10: Ahorro anual por calidad (realizado) | B10: =B8*B9/100 | C10: =C8*C9/100 | D10: =D8*D9/100 | E10: € | G10: =IF($F10="","Derivado (fórmula)","Ver Supuestos (ID "&$F10&")") | H10: Coste_base*reducción
A12: Ahorro anual total (calidad) | B12: =B10 | C12: =C10 | D12: =D10 | E12: €
A14: CQAs considerados en la validación ACQC: densidad@15°C, viscosidad@40°C, TAN e índice de cloro. La reducción de scrap/rework se atribuye a detección temprana y operación dentro de especificación (modo asesor).

Sheet Beneficios_Disponibilidad
A1: Beneficios — Disponibilidad y rendimiento
A2: Incluye (i) reducción de downtime por fallback/alertas y (ii) mejora esperada de rendimiento/throughput por optimización (modo asesor).
A4: Concepto | B4: Conservador | C4: Base | D4: Ambicioso | E4: Unidad | F4: ID supuesto | G4: Fuente | H4: Notas
A5: Producción anual impactada | B5: =INDEX(Supuestos!$E$4:$G$31, MATCH($F5, Supuestos!$A$4:$A$31, 0), MATCH(B$4, Supuestos!$E$3:$G$3, 0)) | C5: =INDEX(Supuestos!$E$4:$G$31, MATCH($F5, Supuestos!$A$4:$A$31, 0), MATCH(C$4, Supuestos!$E$3:$G$3, 0)) | D5: =INDEX(Supuestos!$E$4:$G$31, MATCH($F5, Supuestos!$A$4:$A$31, 0), MATCH(D$4, Supuestos!$E$3:$G$3, 0)) | E5: t/año | F5: P01 | G5: =IF($F5="","Derivado (fórmula)","Ver Supuestos (ID "&$F5&")")
A6: Horas por año | B6: =INDEX(Supuestos!$E$4:$G$31, MATCH($F6, Supuestos!$A$4:$A$31, 0), MATCH(B$4, Supuestos!$E$3:$G$3, 0)) | C6: =INDEX(Supuestos!$E$4:$G$31, MATCH($F6, Supuestos!$A$4:$A$31, 0), MATCH(C$4, Supuestos!$E$3:$G$3, 0)) | D6: =INDEX(Supuestos!$E$4:$G$31, MATCH($F6, Supuestos!$A$4:$A$31, 0), MATCH(D$4, Supuestos!$E$3:$G$3, 0)) | E6: h/año | F6: K00 | G6: =IF($F6="","Derivado (fórmula)","Ver Supuestos (ID "&$F6&")")
A7: Margen por tonelada | B7: =INDEX(Supuestos!$E$4:$G$31, MATCH($F7, Supuestos!$A$4:$A$31, 0), MATCH(B$4, Supuestos!$E$3:$G$3, 0)) | C7: =INDEX(Supuestos!$E$4:$G$31, MATCH($F7, Supuestos!$A$4:$A$31, 0), MATCH(C$4, Supuestos!$E$3:$G$3, 0)) | D7: =INDEX(Supuestos!$E$4:$G$31, MATCH($F7, Supuestos!$A$4:$A$31, 0), MATCH(D$4, Supuestos!$E$3:$G$3, 0)) | E7: €/t | F7: P02 | G7: =IF($F7="","Derivado (fórmula)","Ver Supuestos (ID "&$F7&")")
A8: Downtime anual (baseline) | B8: =INDEX(Supuestos!$E$4:$G$31, MATCH($F8, Supuestos!$A$4:$A$31, 0), MATCH(B$4, Supuestos!$E$3:$G$3, 0)) | C8: =INDEX(Supuestos!$E$4:$G$31, MATCH($F8, Supuestos!$A$4:$A$31, 0), MATCH(C$4, Supuestos!$E$3:$G$3, 0)) | D8: =INDEX(Supuestos!$E$4:$G$31, MATCH($F8, Supuestos!$A$4:$A$31, 0), MATCH(D$4, Supuestos!$E$3:$G$3, 0)) | E8: h/año | F8: A02 | G8: =IF($F8="","Derivado (fórmula)","Ver Supuestos (ID "&$F8&")")
A9: Reducción downtime por ACQC | B9: =INDEX(Supuestos!$E$4:$G$31, MATCH($F9, Supuestos!$A$4:$A$31, 0), MATCH(B$4, Supuestos!$E$3:$G$3, 0)) | C9: =INDEX(Supuestos!$E$4:$G$31, MATCH($F9, Supuestos!$A$4:$A$31, 0), MATCH(C$4, Supuestos!$E$3:$G$3, 0)) | D9: =INDEX(Supuestos!$E$4:$G$31, MATCH($F9, Supuestos!$A$4:$A$31, 0), MATCH(D$4, Supuestos!$E$3:$G$3, 0)) | E9: % | F9: A03 | G9: =IF($F9="","Derivado (fórmula)","Ver Supuestos (ID "&$F9&")")
A10: Producción perdida por downtime (t/año) | B10: =B5/B6*B8 | C10: =C5/C6*C8 | D10: =D5/D6*D8 | E10: t/año | G10: =IF($F10="","Derivado (fórmula)","Ver Supuestos (ID "&$F10&")")
A11: Coste anual por downtime (margen perdido) | B11: =B10*B7 | C11: =C10*C7 | D11: =D10*D7 | E11: € | G11: =IF($F11="","Derivado (fórmula)","Ver Supuestos (ID "&$F11&")")
A12: Ahorro anual por reducción de downtime | B12: =B11*B9/100 | C12: =C11*C9/100 | D12: =D11*D9/100 | E12: € | G12: =IF($F12="","Derivado (fórmula)","Ver Supuestos (ID "&$F12&")")
A13: Mejora throughput/rendimiento por optimización (esperada) | B13: =INDEX(Supuestos!$E$4:$G$31, MATCH($F13, Supuestos!$A$4:$A$31, 0), MATCH(B$4, Supuestos!$E$3:$G$3, 0)) | C13: =INDEX(Supuestos!$E$4:$G$31, MATCH($F13, Supuestos!$A$4:$A$31, 0), MATCH(C$4, Supuestos!$E$3:$G$3, 0)) | D13: =INDEX(Supuestos!$E$4:$G$31, MATCH($F13, Supuestos!$A$4:$A$31, 0), MATCH(D$4, Supuestos!$E$3:$G$3, 0)) | E13: % | F13: P03 | G13: =IF($F13="","Derivado (fórmula)","Ver Supuestos (ID "&$F13&")")
A14: Adopción efectiva (human-in-the-loop) | B14: =INDEX(Supuestos!$E$4:$G$31, MATCH($F14, Supuestos!$A$4:$A$31, 0), MATCH(B$4, Supuestos!$E$3:$G$3, 0)) | C14: =INDEX(Supuestos!$E$4:$G$31, MATCH($F14, Supuestos!$A$4:$A$31, 0), MATCH(C$4, Supuestos!$E$3:$G$3, 0)) | D14: =INDEX(Supuestos!$E$4:$G$31, MATCH($F14, Supuestos!$A$4:$A$31, 0), MATCH(D$4, Supuestos!$E$3:$G$3, 0)) | E14: % | F14: A01 | G14: =IF($F14="","Derivado (fórmula)","Ver Supuestos (ID "&$F14&")")
A15: Beneficio anual por throughput (margen) | B15: =B5*B13/100*B7*B14/100 | C15: =C5*C13/100*C7*C14/100 | D15: =D5*D13/100*D7*D14/100 | E15: € | G15: =IF($F15="","Derivado (fórmula)","Ver Supuestos (ID "&$F15&")")
A16: Beneficio anual total (disponibilidad+rto) | B16: =B12+B15 | C16: =C12+C15 | D16: =D12+D15 | E16: € | G16: =IF($F16="","Derivado (fórmula)","Ver Supuestos (ID "&$F16&")")

Sheet Costes
A1: Costes — CAPEX / OPEX (estimación piloto)
A2: Los costes deben trazarse a cotizaciones, listas internas o entrevistas. Valores actuales son supuestos editables salvo donde se indique fuente.
A4: Concepto | B4: Conservador | C4: Base | D4: Ambicioso | E4: Unidad | F4: ID supuesto | G4: Fuente | H4: Notas
A5: CAPEX — PAT (analizador + instalación) | B5: =INDEX(Supuestos!$E$4:$G$31, MATCH($F5, Supuestos!$A$4:$A$31, 0), MATCH(B$4, Supuestos!$E$3:$G$3, 0)) | C5: =INDEX(Supuestos!$E$4:$G$31, MATCH($F5, Supuestos!$A$4:$A$31, 0), MATCH(C$4, Supuestos!$E$3:$G$3, 0)) | D5: =INDEX(Supuestos!$E$4:$G$31, MATCH($F5, Supuestos!$A$4:$A$31, 0), MATCH(D$4, Supuestos!$E$3:$G$3, 0)) | E5: € | F5: C01 | G5: =IF($F5="","Derivado (fórmula)","Ver Supuestos (ID "&$F5&")")
A6: CAPEX — Edge industrial + armario | B6: =INDEX(Supuestos!$E$4:$G$31, MATCH($F6, Supuestos!$A$4:$A$31, 0), MATCH(B$4, Supuestos!$E$3:$G$3, 0)) | C6: =INDEX(Supuestos!$E$4:$G$31, MATCH($F6, Supuestos!$A$4:$A$31, 0), MATCH(C$4, Supuestos!$E$3:$G$3, 0)) | D6: =INDEX(Supuestos!$E$4:$G$31, MATCH($F6, Supuestos!$A$4:$A$31, 0), MATCH(D$4, Supuestos!$E$3:$G$3, 0)) | E6: € | F6: C02 | G6: =IF($F6="","Derivado (fórmula)","Ver Supuestos (ID "&$F6&")")
A7: CAPEX — Integración OT/IT | B7: =INDEX(Supuestos!$E$4:$G$31, MATCH($F7, Supuestos!$A$4:$A$31, 0), MATCH(B$4, Supuestos!$E$3:$G$3, 0)) | C7: =INDEX(Supuestos!$E$4:$G$31, MATCH($F7, Supuestos!$A$4:$A$31, 0), MATCH(C$4, Supuestos!$E$3:$G$3, 0)) | D7: =INDEX(Supuestos!$E$4:$G$31, MATCH($F7, Supuestos!$A$4:$A$31, 0), MATCH(D$4, Supuestos!$E$3:$G$3, 0)) | E7: € | F7: C03 | G7: =IF($F7="","Derivado (fórmula)","Ver Supuestos (ID "&$F7&")")
A8: CAPEX — Ciberseguridad/hardening | B8: =INDEX(Supuestos!$E$4:$G$31, MATCH($F8, Supuestos!$A$4:$A$31, 0), MATCH(B$4, Supuestos!$E$3:$G$3, 0)) | C8: =INDEX(Supuestos!$E$4:$G$31, MATCH($F8, Supuestos!$A$4:$A$31, 0), MATCH(C$4, Supuestos!$E$3:$G$3, 0)) | D8: =INDEX(Supuestos!$E$4:$G$31, MATCH($F8, Supuestos!$A$4:$A$31, 0), MATCH(D$4, Supuestos!$E$3:$G$3, 0)) | E8: € | F8: C04 | G8: =IF($F8="","Derivado (fórmula)","Ver Supuestos (ID "&$F8&")")
A9: CAPEX — Gestión del cambio/formación | B9: =INDEX(Supuestos!$E$4:$G$31, MATCH($F9, Supuestos!$A$4:$A$31, 0), MATCH(B$4, Supuestos!$E$3:$G$3, 0)) | C9: =INDEX(Supuestos!$E$4:$G$31, MATCH($F9, Supuestos!$A$4:$A$31, 0), MATCH(C$4, Supuestos!$E$3:$G$3, 0)) | D9: =INDEX(Supuestos!$E$4:$G$31, MATCH($F9, Supuestos!$A$4:$A$31, 0), MATCH(D$4, Supuestos!$E$3:$G$3, 0)) | E9: € | F9: C05 | G9: =IF($F9="","Derivado (fórmula)","Ver Supuestos (ID "&$F9&")")
A10: Subtotal CAPEX (sin contingencia) | B10: =SUM(B5:B9) | C10: =SUM(C5:C9) | D10: =SUM(D5:D9) | E10: € | G10: =IF($F10="","Derivado (fórmula)","Ver Supuestos (ID "&$F10&")")
A11: Contingencia CAPEX | B11: =INDEX(Supuestos!$E$4:$G$31, MATCH($F11, Supuestos!$A$4:$A$31, 0), MATCH(B$4, Supuestos!$E$3:$G$3, 0)) | C11: =INDEX(Supuestos!$E$4:$G$31, MATCH($F11, Supuestos!$A$4:$A$31, 0), MATCH(C$4, Supuestos!$E$3:$G$3, 0)) | D11: =INDEX(Supuestos!$E$4:$G$31, MATCH($F11, Supuestos!$A$4:$A$31, 0), MATCH(D$4, Supuestos!$E$3:$G$3, 0)) | E11: % | F11: C06 | G11: =IF($F11="","Derivado (fórmula)","Ver Supuestos (ID "&$F11&")")
A12: Contingencia (€) | B12: =B10*B11/100 | C12: =C10*C11/100 | D12: =D10*D11/100 | E12: € | G12: =IF($F12="","Derivado (fórmula)","Ver Supuestos (ID "&$F12&")")
A13: CAPEX total | B13: =B10+B12 | C13: =C10+C12 | D13: =D10+D12 | E13: € | G13: =IF($F13="","Derivado (fórmula)","Ver Supuestos (ID "&$F13&")")
A16: OPEX anual
A17: OPEX — Mantenimiento PAT | B17: =INDEX(Supuestos!$E$4:$G$31, MATCH($F17, Supuestos!$A$4:$A$31, 0), MATCH(B$4, Supuestos!$E$3:$G$3, 0)) | C17: =INDEX(Supuestos!$E$4:$G$31, MATCH($F17, Supuestos!$A$4:$A$31, 0), MATCH(C$4, Supuestos!$E$3:$G$3, 0)) | D17: =INDEX(Supuestos!$E$4:$G$31, MATCH($F17, Supuestos!$A$4:$A$31, 0), MATCH(D$4, Supuestos!$E$3:$G$3, 0)) | E17: €/año | F17: O01 | G17: =IF($F17="","Derivado (fórmula)","Ver Supuestos (ID "&$F17&")")
A18: OPEX — Soporte MLOps/analítica | B18: =INDEX(Supuestos!$E$4:$G$31, MATCH($F18, Supuestos!$A$4:$A$31, 0), MATCH(B$4, Supuestos!$E$3:$G$3, 0)) | C18: =INDEX(Supuestos!$E$4:$G$31, MATCH($F18, Supuestos!$A$4:$A$31, 0), MATCH(C$4, Supuestos!$E$3:$G$3, 0)) | D18: =INDEX(Supuestos!$E$4:$G$31, MATCH($F18, Supuestos!$A$4:$A$31, 0), MATCH(D$4, Supuestos!$E$3:$G$3, 0)) | E18: €/año | F18: O02 | G18: =IF($F18="","Derivado (fórmula)","Ver Supuestos (ID "&$F18&")")
A19: OPEX — Operación cibersegura | B19: =INDEX(Supuestos!$E$4:$G$31, MATCH($F19, Supuestos!$A$4:$A$31, 0), MATCH(B$4, Supuestos!$E$3:$G$3, 0)) | C19: =INDEX(Supuestos!$E$4:$G$31, MATCH($F19, Supuestos!$A$4:$A$31, 0), MATCH(C$4, Supuestos!$E$3:$G$3, 0)) | D19: =INDEX(Supuestos!$E$4:$G$31, MATCH($F19, Supuestos!$A$4:$A$31, 0), MATCH(D$4, Supuestos!$E$3:$G$3, 0)) | E19: €/año | F19: O03 | G19: =IF($F19="","Derivado (fórmula)","Ver Supuestos (ID "&$F19&")")
A20: OPEX — Infraestructura IT | B20: =INDEX(Supuestos!$E$4:$G$31, MATCH($F20, Supuestos!$A$4:$A$31, 0), MATCH(B$4, Supuestos!$E$3:$G$3, 0)) | C20: =INDEX(Supuestos!$E$4:$G$31, MATCH($F20, Supuestos!$A$4:$A$31, 0), MATCH(C$4, Supuestos!$E$3:$G$3, 0)) | D20: =INDEX(Supuestos!$E$4:$G$31, MATCH($F20, Supuestos!$A$4:$A$31, 0), MATCH(D$4, Supuestos!$E$3:$G$3, 0)) | E20: €/año | F20: O04 | G20: =IF($F20="","Derivado (fórmula)","Ver Supuestos (ID "&$F20&")")
A21: OPEX total anual | B21: =SUM(B17:B20) | C21: =SUM(C17:C20) | D21: =SUM(D17:D20) | E21: €/año | G21: =IF($F21="","Derivado (fórmula)","Ver Supuestos (ID "&$F21&")")

Sheet Sensibilidad
A1: Sensibilidad (±20% en 5 supuestos clave)
A2: Se muestra el impacto en NPV (escenario Base) al variar un supuesto a la vez ±20% (ceteris paribus).
A4: Inputs (Base) usados para sensibilidad
A5: ID | B5: Parámetro | C5: Valor Base | D5: Unidad | E5: Fuente
A6: P01 | B6: Producción anual impactada | C6: =INDEX(Supuestos!$E$4:$G$31, MATCH("P01", Supuestos!$A$4:$A$31, 0), MATCH("Base", Supuestos!$E$3:$G$3, 0)) | D6: t/año | E6: ="Ver Supuestos (ID "&A6&")"
A7: P02 | B7: Margen por tonelada | C7: =INDEX(Supuestos!$E$4:$G$31, MATCH("P02", Supuestos!$A$4:$A$31, 0), MATCH("Base", Supuestos!$E$3:$G$3, 0)) | D7: €/t | E7: ="Ver Supuestos (ID "&A7&")"
A8: P03 | B8: Mejora throughput/rendimiento | C8: =INDEX(Supuestos!$E$4:$G$31, MATCH("P03", Supuestos!$A$4:$A$31, 0), MATCH("Base", Supuestos!$E$3:$G$3, 0)) | D8: % | E8: ="Ver Supuestos (ID "&A8&")"
A9: E01 | B9: Consumo específico | C9: =INDEX(Supuestos!$E$4:$G$31, MATCH("E01", Supuestos!$A$4:$A$31, 0), MATCH("Base", Supuestos!$E$3:$G$3, 0)) | D9: GJ/t | E9: ="Ver Supuestos (ID "&A9&")"
A10: E02 | B10: Precio energía | C10: =INDEX(Supuestos!$E$4:$G$31, MATCH("E02", Supuestos!$A$4:$A$31, 0), MATCH("Base", Supuestos!$E$3:$G$3, 0)) | D10: €/GJ | E10: ="Ver Supuestos (ID "&A10&")"
A11: E03 | B11: % ahorro energía | C11: =INDEX(Supuestos!$E$4:$G$31, MATCH("E03", Supuestos!$A$4:$A$31, 0), MATCH("Base", Supuestos!$E$3:$G$3, 0)) | D11: % | E11: ="Ver Supuestos (ID "&A11&")"
A12: A01 | B12: Adopción efectiva | C12: =INDEX(Supuestos!$E$4:$G$31, MATCH("A01", Supuestos!$A$4:$A$31, 0), MATCH("Base", Supuestos!$E$3:$G$3, 0)) | D12: % | E12: ="Ver Supuestos (ID "&A12&")"
A13: K00 | B13: Horas por año | C13: =INDEX(Supuestos!$E$4:$G$31, MATCH("K00", Supuestos!$A$4:$A$31, 0), MATCH("Base", Supuestos!$E$3:$G$3, 0)) | D13: h/año | E13: ="Ver Supuestos (ID "&A13&")"
A14: A02 | B14: Downtime anual baseline | C14: =INDEX(Supuestos!$E$4:$G$31, MATCH("A02", Supuestos!$A$4:$A$31, 0), MATCH("Base", Supuestos!$E$3:$G$3, 0)) | D14: h/año | E14: ="Ver Supuestos (ID "&A14&")"
A15: A03 | B15: Reducción downtime | C15: =INDEX(Supuestos!$E$4:$G$31, MATCH("A03", Supuestos!$A$4:$A$31, 0), MATCH("Base", Supuestos!$E$3:$G$3, 0)) | D15: % | E15: ="Ver Supuestos (ID "&A15&")"
A16: Q01 | B16: Tasa scrap/rework base | C16: =INDEX(Supuestos!$E$4:$G$31, MATCH("Q01", Supuestos!$A$4:$A$31, 0), MATCH("Base", Supuestos!$E$3:$G$3, 0)) | D16: % | E16: ="Ver Supuestos (ID "&A16&")"
A17: Q02 | B17: Coste scrap/rework | C17: =INDEX(Supuestos!$E$4:$G$31, MATCH("Q02", Supuestos!$A$4:$A$31, 0), MATCH("Base", Supuestos!$E$3:$G$3, 0)) | D17: €/t | E17: ="Ver Supuestos (ID "&A17&")"
A18: Q03 | B18: Reducción scrap/rework | C18: =INDEX(Supuestos!$E$4:$G$31, MATCH("Q03", Supuestos!$A$4:$A$31, 0), MATCH("Base", Supuestos!$E$3:$G$3, 0)) | D18: % | E18: ="Ver Supuestos (ID "&A18&")"
A19: K03 | B19: Vida económica | C19: =INDEX(Supuestos!$E$4:$G$31, MATCH("K03", Supuestos!$A$4:$A$31, 0), MATCH("Base", Supuestos!$E$3:$G$3, 0)) | D19: años | E19: ="Ver Supuestos (ID "&A19&")"
A20: K04 | B20: Tasa de descuento | C20: =INDEX(Supuestos!$E$4:$G$31, MATCH("K04", Supuestos!$A$4:$A$31, 0), MATCH("Base", Supuestos!$E$3:$G$3, 0)) | D20: % | E20: ="Ver Supuestos (ID "&A20&")"
A21: K01 | B21: Factor bajo | C21: =INDEX(Supuestos!$E$4:$G$31, MATCH("K01", Supuestos!$A$4:$A$31, 0), MATCH("Base", Supuestos!$E$3:$G$3, 0)) | D21: x | E21: ="Ver Supuestos (ID "&A21&")"
A22: K02 | B22: Factor alto | C22: =INDEX(Supuestos!$E$4:$G$31, MATCH("K02", Supuestos!$A$4:$A$31, 0), MATCH("Base", Supuestos!$E$3:$G$3, 0)) | D22: x | E22: ="Ver Supuestos (ID "&A22&")"
A24: Costes Base usados en sensibilidad
A25: Elemento | B25: Valor Base | C25: Unidad | D25: Referencia
A26: CAPEX total | B26: =Costes!C13 | C26: € | D26: ="Costes!CAPEX total (Base)"
A27: OPEX total anual | B27: =Costes!C21 | C27: €/año | D27: ="Costes!OPEX total anual (Base)"
A28: NPV Base | B28: =Resumen!C30 | C28: € | D28: ="Resumen!NPV (Base)"
A30: Tabla de sensibilidad (NPV)
A31: Supuesto | B31: ID | C31: Base | D31: Bajo (-20%) | E31: Alto (+20%) | F31: NPV Base | G31: NPV Bajo | H31: NPV Alto | I31: ΔNPV (alto-bajo)
A32: Producción anual impactada | B32: P01 | C32: =$C$6 | D32: =($C$6*$C$21) | E32: =($C$6*$C$22) | F32: =$B$28 | G32: ==-($B$26)+IF($C$20=0,((((($C$6*$C$21)*$C$9*$C$10*$C$11/100*$C$12/100)+(($C$6*$C$21)*$C$16/100*$C$17*$C$18/100)+((($C$6*$C$21)/$C$13*$C$14)*$C$7*$C$15/100)+(($C$6*$C$21)*$C$8/100*$C$7*$C$12/100))-$B$27))*$C$19,((((($C$6*$C$21)*$C$9*$C$10*$C$11/100*$C$12/100)+(($C$6*$C$21)*$C$16/100*$C$17*$C$18/100)+((($C$6*$C$21)/$C$13*$C$14)*$C$7*$C$15/100)+(($C$6*$C$21)*$C$8/100*$C$7*$C$12/100))-$B$27))*(1-(1+$C$20/100)^(-$C$19))/($C$20/100)) | H32: ==-($B$26)+IF($C$20=0,((((($C$6*$C$22)*$C$9*$C$10*$C$11/100*$C$12/100)+(($C$6*$C$22)*$C$16/100*$C$17*$C$18/100)+((($C$6*$C$22)/$C$13*$C$14)*$C$7*$C$15/100)+(($C$6*$C$22)*$C$8/100*$C$7*$C$12/100))-$B$27))*$C$19,((((($C$6*$C$22)*$C$9*$C$10*$C$11/100*$C$12/100)+(($C$6*$C$22)*$C$16/100*$C$17*$C$18/100)+((($C$6*$C$22)/$C$13*$C$14)*$C$7*$C$15/100)+(($C$6*$C$22)*$C$8/100*$C$7*$C$12/100))-$B$27))*(1-(1+$C$20/100)^(-$C$19))/($C$20/100)) | I32: =H32-G32
A33: Precio energía promedio | B33: E02 | C33: =$C$10 | D33: =($C$10*$C$21) | E33: =($C$10*$C$22) | F33: =$B$28 | G33: ==-($B$26)+IF($C$20=0,(((($C$6*$C$9*($C$10*$C$21)*$C$11/100*$C$12/100)+($C$6*$C$16/100*$C$17*$C$18/100)+(($C$6/$C$13*$C$14)*$C$7*$C$15/100)+($C$6*$C$8/100*$C$7*$C$12/100))-$B$27))*$C$19,(((($C$6*$C$9*($C$10*$C$21)*$C$11/100*$C$12/100)+($C$6*$C$16/100*$C$17*$C$18/100)+(($C$6/$C$13*$C$14)*$C$7*$C$15/100)+($C$6*$C$8/100*$C$7*$C$12/100))-$B$27))*(1-(1+$C$20/100)^(-$C$19))/($C$20/100)) | H33: ==-($B$26)+IF($C$20=0,(((($C$6*$C$9*($C$10*$C$22)*$C$11/100*$C$12/100)+($C$6*$C$16/100*$C$17*$C$18/100)+(($C$6/$C$13*$C$14)*$C$7*$C$15/100)+($C$6*$C$8/100*$C$7*$C$12/100))-$B$27))*$C$19,(((($C$6*$C$9*($C$10*$C$22)*$C$11/100*$C$12/100)+($C$6*$C$16/100*$C$17*$C$18/100)+(($C$6/$C$13*$C$14)*$C$7*$C$15/100)+($C$6*$C$8/100*$C$7*$C$12/100))-$B$27))*(1-(1+$C$20/100)^(-$C$19))/($C$20/100)) | I33: =H33-G33
A34: % ahorro energía por optimización | B34: E03 | C34: =$C$11 | D34: =($C$11*$C$21) | E34: =($C$11*$C$22) | F34: =$B$28 | G34: ==-($B$26)+IF($C$20=0,(((($C$6*$C$9*$C$10*($C$11*$C$21)/100*$C$12/100)+($C$6*$C$16/100*$C$17*$C$18/100)+(($C$6/$C$13*$C$14)*$C$7*$C$15/100)+($C$6*$C$8/100*$C$7*$C$12/100))-$B$27))*$C$19,(((($C$6*$C$9*$C$10*($C$11*$C$21)/100*$C$12/100)+($C$6*$C$16/100*$C$17*$C$18/100)+(($C$6/$C$13*$C$14)*$C$7*$C$15/100)+($C$6*$C$8/100*$C$7*$C$12/100))-$B$27))*(1-(1+$C$20/100)^(-$C$19))/($C$20/100)) | H34: ==-($B$26)+IF($C$20=0,(((($C$6*$C$9*$C$10*($C$11*$C$22)/100*$C$12/100)+($C$6*$C$16/100*$C$17*$C$18/100)+(($C$6/$C$13*$C$14)*$C$7*$C$15/100)+($C$6*$C$8/100*$C$7*$C$12/100))-$B$27))*$C$19,(((($C$6*$C$9*$C$10*($C$11*$C$22)/100*$C$12/100)+($C$6*$C$16/100*$C$17*$C$18/100)+(($C$6/$C$13*$C$14)*$C$7*$C$15/100)+($C$6*$C$8/100*$C$7*$C$12/100))-$B$27))*(1-(1+$C$20/100)^(-$C$19))/($C$20/100)) | I34: =H34-G34
A35: Reducción scrap/rework por ACQC | B35: Q03 | C35: =$C$18 | D35: =($C$18*$C$21) | E35: =($C$18*$C$22) | F35: =$B$28 | G35: ==-($B$26)+IF($C$20=0,(((($C$6*$C$9*$C$10*$C$11/100*$C$12/100)+($C$6*$C$16/100*$C$17*($C$18*$C$21)/100)+(($C$6/$C$13*$C$14)*$C$7*$C$15/100)+($C$6*$C$8/100*$C$7*$C$12/100))-$B$27))*$C$19,(((($C$6*$C$9*$C$10*$C$11/100*$C$12/100)+($C$6*$C$16/100*$C$17*($C$18*$C$21)/100)+(($C$6/$C$13*$C$14)*$C$7*$C$15/100)+($C$6*$C$8/100*$C$7*$C$12/100))-$B$27))*(1-(1+$C$20/100)^(-$C$19))/($C$20/100)) | H35: ==-($B$26)+IF($C$20=0,(((($C$6*$C$9*$C$10*$C$11/100*$C$12/100)+($C$6*$C$16/100*$C$17*($C$18*$C$22)/100)+(($C$6/$C$13*$C$14)*$C$7*$C$15/100)+($C$6*$C$8/100*$C$7*$C$12/100))-$B$27))*$C$19,(((($C$6*$C$9*$C$10*$C$11/100*$C$12/100)+($C$6*$C$16/100*$C$17*($C$18*$C$22)/100)+(($C$6/$C$13*$C$14)*$C$7*$C$15/100)+($C$6*$C$8/100*$C$7*$C$12/100))-$B$27))*(1-(1+$C$20/100)^(-$C$19))/($C$20/100)) | I35: =H35-G35
A36: CAPEX total | B36: CAPEX | C36: =$B$26 | D36: =($B$26*$C$21) | E36: =($B$26*$C$22) | F36: =$B$28 | G36: ==-(($B$26*$C$21))+IF($C$20=0,(((($C$6*$C$9*$C$10*$C$11/100*$C$12/100)+($C$6*$C$16/100*$C$17*$C$18/100)+(($C$6/$C$13*$C$14)*$C$7*$C$15/100)+($C$6*$C$8/100*$C$7*$C$12/100))-$B$27))*$C$19,(((($C$6*$C$9*$C$10*$C$11/100*$C$12/100)+($C$6*$C$16/100*$C$17*$C$18/100)+(($C$6/$C$13*$C$14)*$C$7*$C$15/100)+($C$6*$C$8/100*$C$7*$C$12/100))-$B$27))*(1-(1+$C$20/100)^(-$C$19))/($C$20/100)) | H36: ==-(($B$26*$C$22))+IF($C$20=0,(((($C$6*$C$9*$C$10*$C$11/100*$C$12/100)+($C$6*$C$16/100*$C$17*$C$18/100)+(($C$6/$C$13*$C$14)*$C$7*$C$15/100)+($C$6*$C$8/100*$C$7*$C$12/100))-$B$27))*$C$19,(((($C$6*$C$9*$C$10*$C$11/100*$C$12/100)+($C$6*$C$16/100*$C$17*$C$18/100)+(($C$6/$C$13*$C$14)*$C$7*$C$15/100)+($C$6*$C$8/100*$C$7*$C$12/100))-$B$27))*(1-(1+$C$20/100)^(-$C$19))/($C$20/100)) | I36: =H36-G36

Sheet Trazabilidad
A1: Trazabilidad de supuestos (fuentes y pendientes)
A2: Cada supuesto/entrada numérica debe trazar a: documento ACQC, entrevista, histórico o cotización. Completar columnas 'Sección' y 'Evidencia' durante el piloto.
A3: ID | B3: Parámetro | C3: Tipo | D3: Documento | E3: Sección | F3: Evidencia | G3: Owner | H3: Estado | I3: URL/Referencia
A4: K00 | B4: Horas por año | C4: SUPUESTO | D4: — | E4: — | F4: Constante de calendario (sin año específico). | Recolectar evidencia: entrevistas + historian + LIMS + compras. | G4: TFM | H4: PENDIENTE | I4: https://github.com/tangodelta217/ACQC
A5: K01 | B5: Factor sensibilidad (bajo) | C5: SUPUESTO | D5: — | E5: — | F5: Definición interna: ±20% (bajo). | Recolectar evidencia: entrevistas + historian + LIMS + compras. | G5: TFM | H5: PENDIENTE | I5: https://github.com/tangodelta217/ACQC
A6: K02 | B6: Factor sensibilidad (alto) | C6: SUPUESTO | D6: — | E6: — | F6: Definición interna: ±20% (alto). | Recolectar evidencia: entrevistas + historian + LIMS + compras. | G6: TFM | H6: PENDIENTE | I6: https://github.com/tangodelta217/ACQC
A7: K03 | B7: Vida económica del caso | C7: SUPUESTO | D7: — | E7: — | F7: Supuesto estándar para pilotos industriales; ajustar a política financiera. | Recolectar evidencia: entrevistas + historian + LIMS + compras. | G7: Finanzas | H7: PENDIENTE | I7: https://github.com/tangodelta217/ACQC
A8: K04 | B8: Tasa de descuento (WACC/CoC) | C8: SUPUESTO | D8: — | E8: — | F8: Supuesto inicial; reemplazar por tasa corporativa. | Recolectar evidencia: entrevistas + historian + LIMS + compras. | G8: Finanzas | H8: PENDIENTE | I8: https://github.com/tangodelta217/ACQC
A9: A01 | B9: Adopción efectiva de recomendaciones (human-in-the-loop) | C9: SUPUESTO | D9: — | E9: — | F9: Modo asesor con operador en el bucle; adopción parcial es realista. | Recolectar evidencia: entrevistas + historian + LIMS + compras. | G9: Operación | H9: PENDIENTE | I9: https://github.com/tangodelta217/ACQC
A10: A02 | B10: Horas de downtime anual atribuible a incidencias de medición/calidad | C10: SUPUESTO | D10: — | E10: — | F10: Depende de histórico local; establecer con OT/Operación. | Recolectar evidencia: entrevistas + historian + LIMS + compras. | G10: OT/Operación | H10: PENDIENTE | I10: https://github.com/tangodelta217/ACQC
A11: A03 | B11: Reducción de downtime por fallback + detección (ACQC) | C11: SUPUESTO | D11: — | E11: — | F11: Se incluyen flujos degradados (fallback) y observabilidad; cuantificar con incidentes reales. | Recolectar evidencia: entrevistas + historian + LIMS + compras. | G11: OT/Operación | H11: PENDIENTE | I11: https://github.com/tangodelta217/ACQC
A12: P01 | B12: Producción anual impactada (corriente/unidad objetivo) | C12: SUPUESTO | D12: — | E12: — | F12: Requiere definir unidad y corriente en Puertollano; placeholder editable. | Recolectar evidencia: entrevistas + historian + LIMS + compras. | G12: Producción | H12: PENDIENTE | I12: https://github.com/tangodelta217/ACQC
A13: P02 | B13: Margen de contribución por tonelada (producto afectado) | C13: SUPUESTO | D13: — | E13: — | F13: Depende de slate y mercado; usar contabilidad de gestión. | Recolectar evidencia: entrevistas + historian + LIMS + compras. | G13: Finanzas | H13: PENDIENTE | I13: https://github.com/tangodelta217/ACQC
A14: P03 | B14: Mejora de throughput/rendimiento por optimización (esperada) | C14: FUENTE | D14: ACQC_Optimizacion.pdf | E14: Resultados esperados (throughput) | F14: Resultados esperados en simulación/estudios del módulo de optimización segura (no medido en planta). | G14: Proceso | H14: REFERENCIADO | I14: https://github.com/tangodelta217/ACQC
... A31: O04 | B31: Infraestructura IT (almacenamiento, backups, licencias) | C31: SUPUESTO | D31: — | E31: — | F31: Puede ser 0 si se usa infraestructura existente; confirmar. | Recolectar evidencia: entrevistas + historian + LIMS + compras. | G31: IT | H31: PENDIENTE | I31: https://github.com/tangodelta217/ACQC
